colbert/__init__.py
colbert/index.py
colbert/index_updater.py
colbert/indexer.py
colbert/parameters.py
colbert/searcher.py
colbert/trainer.py
colbert/data/__init__.py
colbert/data/collection.py
colbert/data/dataset.py
colbert/data/examples.py
colbert/data/queries.py
colbert/data/ranking.py
colbert/evaluation/__init__.py
colbert/evaluation/load_model.py
colbert/evaluation/loaders.py
colbert/evaluation/metrics.py
colbert/indexing/__init__.py
colbert/indexing/collection_encoder.py
colbert/indexing/collection_indexer.py
colbert/indexing/index_manager.py
colbert/indexing/index_saver.py
colbert/indexing/loaders.py
colbert/indexing/utils.py
colbert/indexing/codecs/__init__.py
colbert/indexing/codecs/decompress_residuals.cpp
colbert/indexing/codecs/decompress_residuals.cu
colbert/indexing/codecs/packbits.cpp
colbert/indexing/codecs/packbits.cu
colbert/indexing/codecs/residual.py
colbert/indexing/codecs/residual_embeddings.py
colbert/indexing/codecs/residual_embeddings_strided.py
colbert/infra/__init__.py
colbert/infra/launcher.py
colbert/infra/provenance.py
colbert/infra/run.py
colbert/infra/config/__init__.py
colbert/infra/config/base_config.py
colbert/infra/config/config.py
colbert/infra/config/core_config.py
colbert/infra/config/settings.py
colbert/modeling/__init__.py
colbert/modeling/base_colbert.py
colbert/modeling/checkpoint.py
colbert/modeling/colbert.py
colbert/modeling/hf_colbert.py
colbert/modeling/segmented_maxsim.cpp
colbert/modeling/reranker/__init__.py
colbert/modeling/reranker/electra.py
colbert/modeling/reranker/tokenizer.py
colbert/modeling/tokenization/__init__.py
colbert/modeling/tokenization/doc_tokenization.py
colbert/modeling/tokenization/query_tokenization.py
colbert/modeling/tokenization/utils.py
colbert/ranking/__init__.py
colbert/search/__init__.py
colbert/search/candidate_generation.py
colbert/search/decompress_residuals.cpp
colbert/search/filter_pids.cpp
colbert/search/index_loader.py
colbert/search/index_storage.py
colbert_modern-0.1.0.dist-info/licenses/LICENSE
colbert_modern-0.1.0.dist-info/METADATA
colbert_modern-0.1.0.dist-info/WHEEL
colbert_modern-0.1.0.dist-info/top_level.txt
colbert_modern-0.1.0.dist-info/RECORD
