Metadata-Version: 2.4
Name: colbert-modern
Version: 0.1.0
Summary: Updated ColBERT: Efficient and Effective Neural Retrieval
Home-page: https://github.com/stanford-futuredata/ColBERT
Author: Estin Chin
Author-email: estin68@gmail.com
Classifier: Programming Language :: Python :: 3
Classifier: License :: OSI Approved :: MIT License
Requires-Python: >=3.8
License-File: LICENSE
Requires-Dist: bitarray
Requires-Dist: datasets
Requires-Dist: flask
Requires-Dist: GitPython
Requires-Dist: python-dotenv
Requires-Dist: ninja
Requires-Dist: scipy
Requires-Dist: tqdm
Requires-Dist: transformers
Requires-Dist: ujson
Provides-Extra: faiss-gpu
Requires-Dist: faiss-gpu>=1.7.0; extra == "faiss-gpu"
Provides-Extra: faiss-cpu
Requires-Dist: faiss-cpu>=1.7.0; extra == "faiss-cpu"
Provides-Extra: torch
Requires-Dist: torch==1.13.1; extra == "torch"
Dynamic: author
Dynamic: author-email
Dynamic: classifier
Dynamic: description
Dynamic: description-content-type
Dynamic: home-page
Dynamic: license-file
Dynamic: provides-extra
Dynamic: requires-dist
Dynamic: requires-python
Dynamic: summary
